fiddle/Builder.py
fiddle/CProtoParser.py
fiddle/Code.py
fiddle/Data.py
fiddle/LocalRunner.py
fiddle/MakeBuilder.py
fiddle/Parameters.py
fiddle/ProtoParser.py
fiddle/Runner.py
fiddle/__init__.py
fiddle/config.py
fiddle/source.py
fiddle/util.py
fiddle/CFG/__init__.py
fiddle/CFG/cfg.py
fiddle/jupyter/__init__.py
fiddle/jupyter/source.py
fiddle/jupyter/util.py
fiddle/perfcount/PerformanceCounterSpec.py
fiddle/perfcount/__init__.py
fiddle/perfcount/perfcount.py
fiddle/perfcount/perfcount_defs.py
fiddle/resources/include/DataSet.hpp
fiddle/resources/include/PerfCounter.hpp
fiddle/resources/include/PerfCounterDefs.hpp
fiddle/resources/include/csv.hpp
fiddle/resources/include/fastrand.h
fiddle/resources/include/fiddle.hpp
fiddle/resources/include/walltime.h
fiddle/resources/libfiddle/Makefile
fiddle/resources/libfiddle/export_perf_count_macros.cpp
fiddle/resources/libfiddle/fiddle.cpp
fiddle/resources/libfiddle/build/export_perf_count_macros
fiddle/resources/libfiddle/build/export_perf_count_macros.d
fiddle/resources/libfiddle/build/export_perf_count_macros.ii
fiddle/resources/libfiddle/build/export_perf_count_macros.o
fiddle/resources/libfiddle/build/export_perf_count_macros.s
fiddle/resources/libfiddle/build/fiddle.d
fiddle/resources/libfiddle/build/fiddle.ii
fiddle/resources/libfiddle/build/fiddle.o
fiddle/resources/libfiddle/build/fiddle.s
fiddle/resources/libfiddle/build/libfiddle.so
fiddle/resources/make/fiddle.make
nvsl_fiddle-0.1.dist-info/LICENSE
nvsl_fiddle-0.1.dist-info/LICENSE.txt
nvsl_fiddle-0.1.dist-info/METADATA
nvsl_fiddle-0.1.dist-info/WHEEL
nvsl_fiddle-0.1.dist-info/entry_points.txt
nvsl_fiddle-0.1.dist-info/top_level.txt
nvsl_fiddle-0.1.dist-info/RECORD
