Metadata-Version: 2.1
Name: nvsl-fiddle
Version: 0.1
Summary: Fiddle makes it easy to ask and answers questions about the compilation and execution of smallish programs written in C or C++.
Home-page: UNKNOWN
License: UNKNOWN
Platform: UNKNOWN
Classifier: Development Status :: 3 - Alpha
Classifier: Intended Audience :: Developers
Classifier: Intended Audience :: Education
Classifier: Topic :: Education
Classifier: Topic :: Education :: Computer Aided Instruction (CAI)
Classifier: Topic :: Software Development :: Compilers
Classifier: Framework :: Jupyter
Classifier: License :: OSI Approved :: MIT License
Classifier: Programming Language :: Python :: 3
Classifier: Programming Language :: Python :: 3.6
Classifier: Programming Language :: Python :: 3.7
Classifier: Programming Language :: Python :: 3.8
Classifier: Programming Language :: Python :: 3.9
Classifier: Programming Language :: Python :: 3.10
License-File: LICENSE
License-File: LICENSE.txt
Requires-Dist: pytest-cpp
Requires-Dist: pytest-xdist
Requires-Dist: click
Requires-Dist: pytest
Requires-Dist: r2pipe
Requires-Dist: pydot
Requires-Dist: networkx
Requires-Dist: pandas
Requires-Dist: IPython
Requires-Dist: nbmake
Requires-Dist: matplotlib
Requires-Dist: tqdm
Requires-Dist: ipywidgets
Requires-Dist: wheel
Requires-Dist: sphinx
Requires-Dist: twine
